ndx_franklab_novela/spec/ndx-franklab-novela.extensions.yaml
ndx_franklab_novela/spec/ndx-franklab-novela.namespace.yaml
ndx_franklab_novela/__init__.py
ndx_franklab_novela-0.2.4.dist-info/METADATA
ndx_franklab_novela-0.2.4.dist-info/WHEEL
ndx_franklab_novela-0.2.4.dist-info/licenses/LICENSE.txt
ndx_franklab_novela-0.2.4.dist-info/RECORD
